mcp_mysql_server/__init__.py
mcp_mysql_server/__main__.py
mcp_mysql_server/server.py
tests/__init__.py
tests/test_server.py
mcp_mysql_bailian_uvx_202509111625_d0a865-2.1.0.dist-info/LICENSE
mcp_mysql_bailian_uvx_202509111625_d0a865-2.1.0.dist-info/METADATA
mcp_mysql_bailian_uvx_202509111625_d0a865-2.1.0.dist-info/WHEEL
mcp_mysql_bailian_uvx_202509111625_d0a865-2.1.0.dist-info/entry_points.txt
mcp_mysql_bailian_uvx_202509111625_d0a865-2.1.0.dist-info/top_level.txt
mcp_mysql_bailian_uvx_202509111625_d0a865-2.1.0.dist-info/RECORD
