Metadata-Version: 2.1
Name: mcp-mysql-bailian-uvx-202509111625-d0a865
Version: 2.1.0
Summary: 阿里云百炼MCP服务器 - MySQL业务查询服务 (UVX兼容版)
Home-page: https://github.com/your-username/mcp-mysql-server
Author: licai-czg
Author-email: your-email@example.com
License: UNKNOWN
Project-URL: Bug Reports, https://github.com/your-username/mcp-mysql-server/issues
Project-URL: Source, https://github.com/your-username/mcp-mysql-server
Keywords: mcp mysql bailian alibaba cloud server uvx
Platform: UNKNOWN
Classifier: Development Status :: 4 - Beta
Classifier: Intended Audience :: Developers
Classifier: License :: OSI Approved :: MIT License
Classifier: Operating System :: OS Independent
Classifier: Programming Language :: Python :: 3
Classifier: Programming Language :: Python :: 3.8
Classifier: Programming Language :: Python :: 3.9
Classifier: Programming Language :: Python :: 3.10
Classifier: Programming Language :: Python :: 3.11
Classifier: Programming Language :: Python :: 3.12
Requires-Python: >=3.8
License-File: LICENSE
Requires-Dist: fastmcp>=0.1.0
Requires-Dist: pymysql>=1.0.0
Requires-Dist: uvicorn>=0.20.0
Requires-Dist: pydantic>=2.0.0
